Metadata-Version: 2.1
Name: gitfiles
Version: 1.0.0
Summary: Load, filter and match .gitingore files
Home-page: https://github.com/legopitstop/gitfiles/
Author: Legopitstop
Author-email: contact@lpsmods.dev
License: MIT
Project-URL: Download, https://github.com/legopitstop/gitfiles/releases
Project-URL: Documentation, https://docs.lpsmods.dev/gitfiles
Project-URL: Source Code, https://github.com/legopitstop/gitfiles
Keywords: gitingore,github,filter,match,pattern
Classifier: Development Status :: 4 - Beta
Classifier: Intended Audience :: Developers
Classifier: License :: OSI Approved :: MIT License
Classifier: Programming Language :: Python :: 3.12
Requires-Python: >=3.8
License-File: LICENSE
